Metadata-Version: 2.1
Name: smthforthetest1337
Version: 0.1
Summary: Testing some weird shit
Author-email: canisvs1dr@gmail.com
